jsconventionfixer/__init__.py
jsconventionfixer/lexema.py
jsconventionfixer/lexer.py
jsconventionfixer/main.py
jsconventionfixer/naming_fixer.py
jsconventionfixer/parser.py
jsconventionfixer-1.1.4.dist-info/METADATA
jsconventionfixer-1.1.4.dist-info/WHEEL
jsconventionfixer-1.1.4.dist-info/entry_points.txt
jsconventionfixer-1.1.4.dist-info/top_level.txt
jsconventionfixer-1.1.4.dist-info/RECORD
