Metadata-Version: 2.1
Name: jsconventionfixer
Version: 1.1.4
Summary: JS code conventions analyzer and fixer
Home-page: https://github.com/scientist19-university/Metaprogramming
Author: Valeriia Yaroshenko
License: UNKNOWN
Platform: UNKNOWN
Requires-Dist: console-progressbar
